linters/__init__.py
linters/length_checker/__init__.py
linters/length_checker/ast_visitor.py
linters/length_checker/code_element.py
linters/length_checker/config.py
linters/length_checker/docstring_finder.py
linters/length_checker/plugin.py
linters/length_checker/statement_counter.py
linters/length_checker/statement_visitor.py
linters/multiple_public_items/__init__.py
linters/multiple_public_items/ast_visitor.py
linters/multiple_public_items/plugin.py
linters/multiple_public_items/public_item.py
pyla_linter-1.3.1.dist-info/METADATA
pyla_linter-1.3.1.dist-info/WHEEL
pyla_linter-1.3.1.dist-info/entry_points.txt
pyla_linter-1.3.1.dist-info/top_level.txt
pyla_linter-1.3.1.dist-info/RECORD
