Metadata-Version: 2.4
Name: pyla-linter
Version: 1.3.1
Summary: Flake8 linting plugins to handle common AI code agent issues
Author: LangAdventure LLC
License: GPL-3.0
Project-URL: Homepage, https://github.com/langadventurellc/pyla-linter
Project-URL: Repository, https://github.com/langadventurellc/pyla-linter
Project-URL: Issues, https://github.com/langadventurellc/pyla-linter/issues
Keywords: linting,flake8,python,langadventure
Classifier: Development Status :: 4 - Beta
Classifier: Intended Audience :: Developers
Classifier: License :: OSI Approved :: GNU General Public License v3 (GPLv3)
Classifier: Programming Language :: Python :: 3
Classifier: Programming Language :: Python :: 3.12
Classifier: Topic :: Software Development :: Libraries :: Python Modules
Classifier: Topic :: Software Development :: Quality Assurance
Requires-Python: >=3.12
Requires-Dist: pyla-logger>=1.0.0
Requires-Dist: flake8>=7.0.0
Requires-Dist: tomli>=2.0.0
Provides-Extra: dev
Requires-Dist: black; extra == "dev"
Requires-Dist: flake8-pyproject; extra == "dev"
Requires-Dist: isort; extra == "dev"
Requires-Dist: poethepoet; extra == "dev"
Requires-Dist: pyright; extra == "dev"
Requires-Dist: pytest; extra == "dev"
Requires-Dist: pytest-mock; extra == "dev"
